setup.cfg
setup.py
codeclimate_test_reporter.egg-info/PKG-INFO
codeclimate_test_reporter.egg-info/SOURCES.txt
codeclimate_test_reporter.egg-info/dependency_links.txt
codeclimate_test_reporter.egg-info/entry_points.txt
codeclimate_test_reporter.egg-info/not-zip-safe
codeclimate_test_reporter.egg-info/requires.txt
codeclimate_test_reporter.egg-info/top_level.txt
reporter/VERSION
reporter/__init__.py
reporter/__main__.py
reporter/components/__init__.py
reporter/components/api_client.py
reporter/components/argument_parser.py
reporter/components/ci.py
reporter/components/file_coverage.py
reporter/components/formatter.py
reporter/components/git_command.py
reporter/components/payload_validator.py
reporter/components/reporter.py
reporter/components/runner.py
reporter/tests/__init__.py
reporter/tests/test_ci.py
reporter/tests/test_formatter.py