Metadata-Version: 1.0
Name: codeclimate-test-reporter
Version: 0.0.4
Summary: Report test coverage to Code Climate
Home-page: http://github.com/codeclimate/python-test-reporter
Author: Code Climate
Author-email: hello@codeclimate.com
License: MIT
Platform: UNKNOWN
